{
    "examen": [
        {
            "seccion": "Sección 1",
            "title": "Pregunta número 2 de la sección 1",
            "descripcion": "Descripción de la pregunta a desarrollar",
            "opciones": "Varias opciones",
            "checkboxtitleopcion": [],
            "titleopcion": []
        },
        {
            "seccion": "Sección 2",
            "id": "a453b7d6-9261-415f-b927-4245a4649327",
            "title": "Pregunta número 2 de la sección 2",
            "descripcion": "Descripción de la pregunta a terminar más adelante",
            "opciones": "Respuesta corta",
            "checkboxtitleopcion": [],
            "titleopcion": []
        },
        {
            "seccion": "Sección 2",
            "id": "f1a58d49-5a85-4b69-8215-8fd4f9c6a3ad",
            "title": "Pregunta número 1 de la sección 2",
            "descripcion": "Descripción de la pregunta a desarrollar",
            "opciones": "Varias opciones",
            "checkboxtitleopcion": "ultima opción",
            "titleopcion": [
                "Opción 1",
                "Opción 2"
            ]
        }
    ]
}